secfi/__init__.py
secfi/secfi.py
secfi-0.1.11.dist-info/LICENSE.txt
secfi-0.1.11.dist-info/METADATA
secfi-0.1.11.dist-info/WHEEL
secfi-0.1.11.dist-info/top_level.txt
secfi-0.1.11.dist-info/RECORD
