Metadata-Version: 2.1
Name: secfi
Version: 0.1.11
Summary: Python tool to collect SEC filings for all publicly traded companies. Easily fetch forms like 10-K, 10-Q, and 8-K, along with links and document contents. Ideal for analysts, researchers, and anyone exploring financial reports or SEC data. Simplify your access to essential company information
Home-page: https://github.com/gauss314/secfi
Author: Juan Pablo
Author-email: Juan Pablo <juanpypython@gmail.com>
License: MIT
Classifier: Development Status :: 3 - Alpha
Classifier: Intended Audience :: Developers
Classifier: License :: OSI Approved :: MIT License
Classifier: Programming Language :: Python :: 3
Classifier: Programming Language :: Python :: 3.6
Classifier: Programming Language :: Python :: 3.7
Classifier: Programming Language :: Python :: 3.8
Classifier: Programming Language :: Python :: 3.9
Requires-Python: >=3.6
License-File: LICENSE.txt
Requires-Dist: beautifulsoup4==4.12.3
Requires-Dist: certifi==2024.8.30
Requires-Dist: charset-normalizer==3.4.0
Requires-Dist: idna==3.10
Requires-Dist: numpy<2.0.0,>=1.23.5
Requires-Dist: pandas==2.2.2
Requires-Dist: python-dateutil==2.9.0.post0
Requires-Dist: pytz==2024.2
Requires-Dist: requests==2.32.3
Requires-Dist: setuptools==75.6.0
Requires-Dist: six==1.16.0
Requires-Dist: soupsieve==2.6
Requires-Dist: tzdata==2024.2
Requires-Dist: urllib3==2.2.3
